tokenfinderbot/__init__.py
tokenfinderbot/db.py
tokenfinderbot/tokenfinderbot.py
tokenfinderbot/utils.py
tokenfinderbot-1.0.2.dist-info/LICENSE
tokenfinderbot-1.0.2.dist-info/METADATA
tokenfinderbot-1.0.2.dist-info/WHEEL
tokenfinderbot-1.0.2.dist-info/RECORD
