Metadata-Version: 2.1
Name: tokenfinderbot
Version: 1.0.2
Summary: A simple bot for scanning new ERC-20 token pools created and filtering them based on the time created, liquidity and market cap
Home-page: https://github.com/farzadex-eth/tokenfinderbot
Author: Farzad Z
Author-email: farzadex.eth@gmail.com
Requires-Python: >=3.10,<4.0
Classifier: Programming Language :: Python :: 3
Classifier: Programming Language :: Python :: 3.10
Classifier: Programming Language :: Python :: 3.11
Requires-Dist: dotmap (>=1.3.30,<2.0.0)
Requires-Dist: pytest (>=7.3.1,<8.0.0)
Requires-Dist: requests (>=2.30.0,<3.0.0)
Requires-Dist: schedule (>=1.2.0,<2.0.0)
Requires-Dist: tinydb (>=4.7.1,<5.0.0)
Project-URL: Repository, https://github.com/farzadex-eth/tokenfinderbot
